{"cameraMode":{"drawMode":0,"name":"Shaded","section":"Shading Mode"},"sceneLighting":true,"audioPlay":false,"sceneViewState":{"m_AlwaysRefresh":false,"showFog":true,"showSkybox":true,"showFlares":true,"showImageEffects":true,"showParticleSystems":true,"showVisualEffectGraphs":true,"m_FxEnabled":true},"in2DMode":false,"pivot":{"x":65.47786712646485,"y":-23.33432388305664,"z":56.40752410888672},"rotation":{"x":0.09984001517295838,"y":0.3485727310180664,"z":-0.037378475069999698,"w":0.9312055110931397},"size":84.35923767089844,"orthographic":false}